flet_stack/__init__.py
flet_stack/router.py
flet_stack-0.3.0.dist-info/licenses/LICENSE
flet_stack-0.3.0.dist-info/METADATA
flet_stack-0.3.0.dist-info/WHEEL
flet_stack-0.3.0.dist-info/top_level.txt
flet_stack-0.3.0.dist-info/RECORD
