Metadata-Version: 2.4
Name: flet-stack
Version: 0.3.0
Summary: Decorator-based routing with view stacking for Flet applications
Home-page: https://github.com/fasilwdr/flet-stack
Author: Fasil
Author-email: Fasil <fasilwdr@hotmail.com>
License: MIT
Project-URL: Homepage, https://github.com/fasilwdr/flet-stack
Project-URL: Documentation, https://github.com/fasilwdr/flet-stack#readme
Project-URL: Repository, https://github.com/fasilwdr/flet-stack
Project-URL: Issues, https://github.com/fasilwdr/flet-stack/issues
Keywords: flet,routing,router,navigation,ui,view-stack
Classifier: Development Status :: 4 - Beta
Classifier: Intended Audience :: Developers
Classifier: License :: OSI Approved :: MIT License
Classifier: Programming Language :: Python :: 3
Classifier: Programming Language :: Python :: 3.9
Classifier: Programming Language :: Python :: 3.10
Classifier: Programming Language :: Python :: 3.11
Classifier: Programming Language :: Python :: 3.12
Classifier: Programming Language :: Python :: 3.13
Classifier: Topic :: Software Development :: Libraries :: Python Modules
Classifier: Topic :: Software Development :: User Interfaces
Requires-Python: >=3.8
License-File: LICENSE
Requires-Dist: flet>=0.70.0.dev6281
Provides-Extra: dev
Requires-Dist: black>=23.0.0; extra == "dev"
Requires-Dist: isort>=5.12.0; extra == "dev"
Requires-Dist: flake8>=6.0.0; extra == "dev"
Dynamic: author
Dynamic: home-page
Dynamic: license-file
Dynamic: requires-python
